LICENSE
MANIFEST.in
README.md
setup.py
preloaded/__init__.py
preloaded/_io.py
preloaded/criu.py
preloaded/fork_server.py
preloaded/py_preloaded_bundle_disk_ckpt.py
preloaded/py_preloaded_bundle_fork_server.py
preloaded/startup.py
preloaded/utils.py
preloaded.egg-info/PKG-INFO
preloaded.egg-info/SOURCES.txt
preloaded.egg-info/dependency_links.txt
preloaded.egg-info/entry_points.txt
preloaded.egg-info/top_level.txt
tests/test_basic.py