Metadata-Version: 2.1
Name: preloaded
Version: 1.20230516.122456
Summary: Python Preloaded - Bundle Python executable with preloaded modules
Home-page: https://github.com/albertz/python-preloaded
Author: Albert Zeyer
Author-email: albzey@gmail.com
License: MIT License
Classifier: Development Status :: 4 - Beta
Classifier: Intended Audience :: Developers
Classifier: Intended Audience :: Education
Classifier: Intended Audience :: Science/Research
Classifier: License :: OSI Approved :: MIT License
Classifier: Operating System :: MacOS :: MacOS X
Classifier: Operating System :: POSIX
Classifier: Operating System :: Unix
Classifier: Programming Language :: Python
Classifier: Topic :: Software Development :: Libraries
Classifier: Topic :: Software Development :: Libraries :: Python Modules
Classifier: Topic :: System
Classifier: Topic :: Utilities
License-File: LICENSE
